slsvd2/__init__.py
slsvd2/data2.py
slsvd2/metrics.py
slsvd2/slsvd2.py
slsvd2-0.1.0.dist-info/LICENSE
slsvd2-0.1.0.dist-info/METADATA
slsvd2-0.1.0.dist-info/WHEEL
slsvd2-0.1.0.dist-info/RECORD
