Metadata-Version: 2.1
Name: slsvd2
Version: 0.1.0
Summary: A package for two-way sparse logistic SVD!
License: MIT
Author: Andy Zhang
Requires-Python: >=3.9,<4.0
Classifier: License :: OSI Approved :: MIT License
Classifier: Programming Language :: Python :: 3
Classifier: Programming Language :: Python :: 3.9
Classifier: Programming Language :: Python :: 3.10
Classifier: Programming Language :: Python :: 3.11
Classifier: Programming Language :: Python :: 3.12
Requires-Dist: matplotlib (>=3.9.0,<4.0.0)
Requires-Dist: scipy (>=1.13.0,<2.0.0)
